{"title":"对苏贸易应从统筹全局出发","alias":"","parts":[{"type":"paragraph","text":"对苏贸易应从统筹全局出发"},{"type":"paragraph","text":"（1949年12月22日）中央："},{"type":"paragraph","text":"（一）据稼祥\"说，波兰、捷克、德国都想和我们做生意。似此，除苏联外又有这三个国家即将发生通商贸易关系。此外，英国、日本、美国、印度等国或已有生意或即将做生意。因此，你们在准备对苏贸易条约时应从统筹全局的观点出发，苏联当然是第一位，但同时要准备和波、捷、德、英、日、美等国做生意，其范围和数量要有一个大概的计算。（二）二十一日来电已收到，已与斯大林约好二十三或二十四日谈一次。在这次谈话后可以确定方针电告你们。"},{"type":"paragraph","text":"毛泽东"},{"type":"paragraph","text":"十二月二十二日上午三时"},{"type":"paragraph","text":"[1]稼祥，即王稼祥（1906—1974），安徽泾县人。当时任中国驻苏联大使。"}],"authors":["毛泽东"],"dates":[{"year":1949,"month":12,"day":22}],"is_range_date":false,"comments":[],"comment_pivots":[],"description":"","page_start":104,"page_end":104}